mongoquery/__init__.py
mongoquery-1.4.2.dist-info/LICENSE
mongoquery-1.4.2.dist-info/METADATA
mongoquery-1.4.2.dist-info/WHEEL
mongoquery-1.4.2.dist-info/top_level.txt
mongoquery-1.4.2.dist-info/RECORD
