Metadata-Version: 2.1
Name: mongoquery
Version: 1.4.2
Summary: A utility library that provides a MongoDB-like query language for querying python collections. It's mainly intended to parse objects structured as fundamental types in a similar fashion to what is produced by JSON or YAML parsers.
Home-page: http://github.com/kapouille/mongoquery
Author: Olivier Carrere
Author-email: olivier.carrere@gmail.com
Keywords: mongodb query match
Classifier: Programming Language :: Python
Classifier: Development Status :: 5 - Production/Stable
Classifier: Programming Language :: Python :: 2
Classifier: Programming Language :: Python :: 3
Classifier: Programming Language :: Python :: Implementation :: CPython
Classifier: Topic :: Utilities
License-File: LICENSE
